spandex
