Metadata-Version: 1.1
Name: spandex
Version: 1.1.2
Summary: Execute elastic-recheck query files and analyze the results.
Home-page: http://github.com/dolph/spandex
Author: Dolph Mathews
Author-email: dolph.mathews@gmail.com
License: UNKNOWN
Platform: UNKNOWN
Classifier: Development Status :: 5 - Production/Stable
Classifier: Environment :: Console
Classifier: Environment :: OpenStack
Classifier: Intended Audience :: Developers
Classifier: Topic :: Utilities
